odoo10_addon_base_view_inheritance_extension-10.0.1.0.1-py2.7-nspkg.pth
odoo/addons/base_view_inheritance_extension/README.rst
odoo/addons/base_view_inheritance_extension/__init__.py
odoo/addons/base_view_inheritance_extension/__manifest__.py
odoo/addons/base_view_inheritance_extension/demo/ir_ui_view.xml
odoo/addons/base_view_inheritance_extension/i18n/ca.po
odoo/addons/base_view_inheritance_extension/i18n/de.po
odoo/addons/base_view_inheritance_extension/i18n/it.po
odoo/addons/base_view_inheritance_extension/i18n/sl.po
odoo/addons/base_view_inheritance_extension/i18n/tr.po
odoo/addons/base_view_inheritance_extension/models/__init__.py
odoo/addons/base_view_inheritance_extension/models/ir_ui_view.py
odoo/addons/base_view_inheritance_extension/static/description/icon.png
odoo/addons/base_view_inheritance_extension/tests/__init__.py
odoo/addons/base_view_inheritance_extension/tests/test_base_view_inheritance_extension.py
odoo10_addon_base_view_inheritance_extension-10.0.1.0.1.dist-info/DESCRIPTION.rst
odoo10_addon_base_view_inheritance_extension-10.0.1.0.1.dist-info/METADATA
odoo10_addon_base_view_inheritance_extension-10.0.1.0.1.dist-info/RECORD
odoo10_addon_base_view_inheritance_extension-10.0.1.0.1.dist-info/WHEEL
odoo10_addon_base_view_inheritance_extension-10.0.1.0.1.dist-info/metadata.json
odoo10_addon_base_view_inheritance_extension-10.0.1.0.1.dist-info/namespace_packages.txt
odoo10_addon_base_view_inheritance_extension-10.0.1.0.1.dist-info/top_level.txt
